scrappey/__init__.py
scrappey/async_client.py
scrappey/client.py
scrappey/exceptions.py
scrappey/py.typed
scrappey/requests.py
scrappey/types.py
scrappey-1.0.3.dist-info/licenses/LICENSE.txt
scrappey-1.0.3.dist-info/METADATA
scrappey-1.0.3.dist-info/WHEEL
scrappey-1.0.3.dist-info/top_level.txt
scrappey-1.0.3.dist-info/RECORD
